[
  {
    "ContainingType": "FastEndpoints.MainExtensions\u002B\u003C\u003Ec",
    "Method": "\u003CMapFastEndpoints\u003Eb__2_1",
    "RelativePath": "Contributors",
    "HttpMethod": "POST",
    "IsController": false,
    "Order": 0,
    "Parameters": [
      {
        "Name": "CreateContributorRequest",
        "Type": "Whispers.Chat.Web.Contributors.CreateContributorRequest",
        "IsRequired": true
      }
    ],
    "ReturnTypes": [
      {
        "Type": "Whispers.Chat.Web.Contributors.CreateContributorResponse",
        "MediaTypes": [
          "application/json"
        ],
        "StatusCode": 200
      }
    ],
    "EndpointName": "WhispersChatWebContributorsCreate"
  },
  {
    "ContainingType": "FastEndpoints.MainExtensions\u002B\u003C\u003Ec",
    "Method": "\u003CMapFastEndpoints\u003Eb__2_1",
    "RelativePath": "Contributors",
    "HttpMethod": "GET",
    "IsController": false,
    "Order": 0,
    "Parameters": [],
    "ReturnTypes": [
      {
        "Type": "Whispers.Chat.Web.Contributors.ContributorListResponse",
        "MediaTypes": [
          "application/json"
        ],
        "StatusCode": 200
      }
    ],
    "EndpointName": "WhispersChatWebContributorsList"
  },
  {
    "ContainingType": "FastEndpoints.MainExtensions\u002B\u003C\u003Ec",
    "Method": "\u003CMapFastEndpoints\u003Eb__2_1",
    "RelativePath": "Contributors/{ContributorId:int}",
    "HttpMethod": "DELETE",
    "IsController": false,
    "Order": 0,
    "Parameters": [
      {
        "Name": "DeleteContributorRequest",
        "Type": "Whispers.Chat.Web.Contributors.DeleteContributorRequest",
        "IsRequired": true
      }
    ],
    "ReturnTypes": [
      {
        "Type": "System.Void",
        "MediaTypes": [],
        "StatusCode": 204
      }
    ],
    "EndpointName": "WhispersChatWebContributorsDelete"
  },
  {
    "ContainingType": "FastEndpoints.MainExtensions\u002B\u003C\u003Ec",
    "Method": "\u003CMapFastEndpoints\u003Eb__2_1",
    "RelativePath": "Contributors/{ContributorId:int}",
    "HttpMethod": "GET",
    "IsController": false,
    "Order": 0,
    "Parameters": [
      {
        "Name": "GetContributorByIdRequest",
        "Type": "Whispers.Chat.Web.Contributors.GetContributorByIdRequest",
        "IsRequired": true
      }
    ],
    "ReturnTypes": [
      {
        "Type": "Whispers.Chat.Web.Contributors.ContributorRecord",
        "MediaTypes": [
          "application/json"
        ],
        "StatusCode": 200
      }
    ],
    "EndpointName": "WhispersChatWebContributorsGetById"
  },
  {
    "ContainingType": "FastEndpoints.MainExtensions\u002B\u003C\u003Ec",
    "Method": "\u003CMapFastEndpoints\u003Eb__2_1",
    "RelativePath": "Contributors/{ContributorId:int}",
    "HttpMethod": "PUT",
    "IsController": false,
    "Order": 0,
    "Parameters": [
      {
        "Name": "UpdateContributorRequest",
        "Type": "Whispers.Chat.Web.Contributors.UpdateContributorRequest",
        "IsRequired": true
      }
    ],
    "ReturnTypes": [
      {
        "Type": "Whispers.Chat.Web.Contributors.UpdateContributorResponse",
        "MediaTypes": [
          "application/json"
        ],
        "StatusCode": 200
      }
    ],
    "EndpointName": "WhispersChatWebContributorsUpdate"
  }
]